<ColorMaps>
<ColorMap space="CIELAB" indexedLookup="false" name="RB5_7D">
<Point x="0.000000" o="1" r="1.000000" g="0.945098" b="0.839216"/>
<Point x="0.050000" o="1" r="0.941176" g="0.870588" b="0.760784"/>
<Point x="0.100000" o="1" r="0.878431" g="0.756863" b="0.600000"/>
<Point x="0.150000" o="1" r="0.819608" g="0.678431" b="0.525490"/>
<Point x="0.200000" o="1" r="0.780392" g="0.623529" b="0.482353"/>
<Point x="0.250000" o="1" r="0.741176" g="0.568627" b="0.443137"/>
<Point x="0.300000" o="1" r="0.709804" g="0.521569" b="0.411765"/>
<Point x="0.350000" o="1" r="0.670588" g="0.466667" b="0.376471"/>
<Point x="0.400000" o="1" r="0.639216" g="0.423529" b="0.345098"/>
<Point x="0.450000" o="1" r="0.611765" g="0.380392" b="0.317647"/>
<Point x="0.500000" o="1" r="0.580392" g="0.345098" b="0.290196"/>
<Point x="0.550000" o="1" r="0.549020" g="0.309804" b="0.270588"/>
<Point x="0.600000" o="1" r="0.521569" g="0.282353" b="0.250980"/>
<Point x="0.650000" o="1" r="0.490196" g="0.250980" b="0.231373"/>
<Point x="0.700000" o="1" r="0.458824" g="0.223529" b="0.211765"/>
<Point x="0.750000" o="1" r="0.431373" g="0.196078" b="0.192157"/>
<Point x="0.800000" o="1" r="0.400000" g="0.172549" b="0.184314"/>
<Point x="0.850000" o="1" r="0.368627" g="0.152941" b="0.168627"/>
<Point x="0.900000" o="1" r="0.329412" g="0.129412" b="0.152941"/>
<Point x="0.950000" o="1" r="0.290196" g="0.105882" b="0.133333"/>
<Point x="1.000000" o="1" r="0.250980" g="0.086275" b="0.113725"/>
<NaN r="0.25" g="0" b="0"/>
</ColorMap>
</ColorMaps>
